ledgers/__init__.py
ledgers/apps.py
ledgers/enum.py
ledgers/ledger/__init__.py
ledgers/ledger/cumulative.py
ledgers/ledger/meta.py
ledgers/ledger/fields/__init__.py
ledgers/ledger/fields/base.py
ledgers/ledger/fields/dimensions.py
ledgers/ledger/fields/resources.py
ledgers/migrations/0001_initial.py
ledgers/migrations/__init__.py
ledgers/models/__init__.py
ledgers/models/documents/__init__.py
ledgers/models/documents/document.py
ledgers/models/documents/iterator.py
ledgers/models/ledgers/__init__.py
ledgers/models/ledgers/movements.py
ledgers/models/ledgers/totals.py
ledgers/models/ledgers/bases/__init__.py
ledgers/models/ledgers/bases/dependent.py
ledgers/models/ledgers/bases/periodic.py
ledgers/utils/__init__.py
ledgers/utils/arrays.py
ledgers/utils/decorators.py
django_ledgers-0.1.0.dist-info/LICENSE
django_ledgers-0.1.0.dist-info/METADATA
django_ledgers-0.1.0.dist-info/WHEEL
django_ledgers-0.1.0.dist-info/top_level.txt
django_ledgers-0.1.0.dist-info/RECORD
