Metadata-Version: 2.1
Name: django-ledgers
Version: 0.1.0
Summary: Django app which implements ledgers to store cumulative data.
Home-page: https://github.com/omelched/django-ledgers
Author: Denis Omelchenko
Author-email: omelched@gmail.com
Project-URL: Bug Tracker, https://github.com/omelched/django-ledgers/issues
Project-URL: Changelog, https://github.com/omelched/django-ledgers/releases
Classifier: Development Status :: 3 - Alpha
Classifier: Environment :: Web Environment
Classifier: Framework :: Django
Classifier: Framework :: Django :: 4.2
Classifier: Intended Audience :: Developers
Classifier: License :: OSI Approved :: MIT License
Classifier: Operating System :: OS Independent
Classifier: Natural Language :: English
Classifier: Programming Language :: Python
Classifier: Programming Language :: Python :: 3
Classifier: Programming Language :: Python :: 3.9
Classifier: Programming Language :: Python :: 3.10
Classifier: Programming Language :: Python :: 3.11
Classifier: Topic :: Database
Classifier: Topic :: Internet
Classifier: Topic :: Internet :: WWW/HTTP
Classifier: Topic :: Utilities
Requires-Python: >=3.9
License-File: LICENSE
Requires-Dist: django
Requires-Dist: django-cte
